haltstate/__init__.py
haltstate_sdk-0.6.0.dist-info/licenses/LICENSE
janus/__init__.py
janus/async_client.py
janus/client.py
janus/decorators.py
janus/exceptions.py
janus/models.py
haltstate_sdk-0.6.0.dist-info/METADATA
haltstate_sdk-0.6.0.dist-info/WHEEL
haltstate_sdk-0.6.0.dist-info/top_level.txt
haltstate_sdk-0.6.0.dist-info/RECORD
