Metadata-Version: 2.4
Name: haltstate-sdk
Version: 0.6.0
Summary: HaltState Sentinel Python SDK - Compliance & Policy Checks for AI Agents
Author-email: Krystal Unity <support@krystalunity.com>
License: MIT License
Project-URL: Homepage, https://haltstate.ai
Project-URL: Repository, https://github.com/StartKrystal/krystal-unity-core
Project-URL: Issues, https://github.com/StartKrystal/krystal-unity-core/issues
Project-URL: Documentation, https://haltstate.ai/docs
Keywords: haltstate,janus,sentinel,ai,compliance,policy,sdk,safety
Classifier: Development Status :: 4 - Beta
Classifier: Intended Audience :: Developers
Classifier: License :: OSI Approved :: MIT License
Classifier: Programming Language :: Python :: 3
Classifier: Programming Language :: Python :: 3.9
Classifier: Programming Language :: Python :: 3.10
Classifier: Programming Language :: Python :: 3.11
Classifier: Programming Language :: Python :: 3.12
Classifier: Topic :: Software Development :: Libraries :: Python Modules
Classifier: Topic :: Security
Requires-Python: >=3.9
License-File: LICENSE
Requires-Dist: httpx>=0.24
Dynamic: license-file
